[{"showyear": "1998", "city": "Uniondale", "showid": "1252683825", "relativetime": "16 years ago", "artist": "Phish", "country": "USA", "nicedate": "April 02, 1998", "venue": "Nassau Coliseum", "state": "NY", "meta": "", "link": "http://phish.net/setlists/?d=1998-04-02", "venueid": "242", "showdate": "1998-04-02"}, {"showyear": "1998", "city": "Uniondale", "showid": "1252692935", "relativetime": "16 years ago", "artist": "Phish", "country": "USA", "nicedate": "April 03, 1998", "venue": "Nassau Coliseum", "state": "NY", "meta": "", "link": "http://phish.net/setlists/?d=1998-04-03", "venueid": "242", "showdate": "1998-04-03"}, {"showyear": "1998", "city": "Providence", "showid": "1252693155", "relativetime": "16 years ago", "artist": "Phish", "country": "USA", "nicedate": "April 04, 1998", "venue": "Providence Civic Center", "state": "RI", "meta": "", "link": "http://phish.net/setlists/?d=1998-04-04", "venueid": "440", "showdate": "1998-04-04"}, {"showyear": "1998", "city": "Providence", "showid": "1252697546", "relativetime": "16 years ago", "artist": "Phish", "country": "USA", "nicedate": "April 05, 1998", "venue": "Providence Civic Center", "state": "RI", "meta": "", "link": "http://phish.net/setlists/?d=1998-04-05", "venueid": "440", "showdate": "1998-04-05"}, {"showyear": "1998", "city": "Freetown Christiana, Copenhagen", "showid": "1254091398", "relativetime": "16 years ago", "artist": "Phish", "country": "Denmark", "nicedate": "June 29, 1998", "venue": "The Grey Hall", "state": "", "meta": "", "link": "http://phish.net/setlists/?d=1998-06-29", "venueid": "11", "showdate": "1998-06-29"}, {"showyear": "1998", "city": "Freetown Christiana, Copenhagen", "showid": "1252698017", "relativetime": "16 years ago", "artist": "Phish", "country": "Denmark", "nicedate": "June 30, 1998", "venue": "The Grey Hall", "state": "", "meta": "", "link": "http://phish.net/setlists/?d=1998-06-30", "venueid": "11", "showdate": "1998-06-30"}, {"showyear": "1998", "city": "Freetown Christiana, Copenhagen", "showid": "1252698193", "relativetime": "16 years ago", "artist": "Phish", "country": "Denmark", "nicedate": "July 01, 1998", "venue": "The Grey Hall", "state": "", "meta": "", "link": "http://phish.net/setlists/?d=1998-07-01", "venueid": "11", "showdate": "1998-07-01"}, {"showyear": "1998", "city": "Freetown Christiana, Copenhagen", "showid": "1250019273", "relativetime": "16 years ago", "artist": "Phish", "country": "Denmark", "nicedate": "July 02, 1998", "venue": "The Grey Hall", "state": "", "meta": "", "link": "http://phish.net/setlists/?d=1998-07-02", "venueid": "11", "showdate": "1998-07-02"}, {"showyear": "1998", "city": "Ringe, Fyn", "showid": "1252698870", "relativetime": "16 years ago", "artist": "Phish", "country": "Denmark", "nicedate": "July 03, 1998", "venue": "Dyrskuepladsen", "state": "", "meta": "", "link": "http://phish.net/setlists/?d=1998-07-03", "venueid": "530", "showdate": "1998-07-03"}, {"showyear": "1998", "city": "Prague", "showid": "1252699030", "relativetime": "16 years ago", "artist": "Phish", "country": "Czech Republic", "nicedate": "July 05, 1998", "venue": "Lucerna Theatre", "state": "", "meta": "", "link": "http://phish.net/setlists/?d=1998-07-05", "venueid": "531", "showdate": "1998-07-05"}, {"showyear": "1998", "city": "Prague", "showid": "1252699225", "relativetime": "16 years ago", "artist": "Phish", "country": "Czech Republic", "nicedate": "July 06, 1998", "venue": "Lucerna Theatre", "state": "", "meta": "", "link": "http://phish.net/setlists/?d=1998-07-06", "venueid": "531", "showdate": "1998-07-06"}, {"showyear": "1998", "city": "Barcelona", "showid": "1252702771", "relativetime": "16 years ago", "artist": "Phish", "country": "Spain", "nicedate": "July 08, 1998", "venue": "Zeleste", "state": "", "meta": "", "link": "http://phish.net/setlists/?d=1998-07-08", "venueid": "12", "showdate": "1998-07-08"}, {"showyear": "1998", "city": "Barcelona", "showid": "1252703054", "relativetime": "16 years ago", "artist": "Phish", "country": "Spain", "nicedate": "July 09, 1998", "venue": "Zeleste", "state": "", "meta": "", "link": "http://phish.net/setlists/?d=1998-07-09", "venueid": "12", "showdate": "1998-07-09"}, {"showyear": "1998", "city": "Barcelona", "showid": "1250024745", "relativetime": "16 years ago", "artist": "Phish", "country": "Spain", "nicedate": "July 10, 1998", "venue": "Zeleste", "state": "", "meta": "", "link": "http://phish.net/setlists/?d=1998-07-10", "venueid": "12", "showdate": "1998-07-10"}, {"showyear": "1998", "city": "Portland", "showid": "1252705711", "relativetime": "15 years ago", "artist": "Phish", "country": "USA", "nicedate": "July 15, 1998", "venue": "Portland Meadows", "state": "OR", "meta": "", "link": "http://phish.net/setlists/?d=1998-07-15", "venueid": "412", "showdate": "1998-07-15"}, {"showyear": "1998", "city": "George", "showid": "1252705942", "relativetime": "15 years ago", "artist": "Phish", "country": "USA", "nicedate": "July 16, 1998", "venue": "Gorge Amphitheatre", "state": "WA", "meta": "", "link": "http://phish.net/setlists/?d=1998-07-16", "venueid": "248", "showdate": "1998-07-16"}, {"showyear": "1998", "city": "George", "showid": "1252706128", "relativetime": "15 years ago", "artist": "Phish", "country": "USA", "nicedate": "July 17, 1998", "venue": "Gorge Amphitheatre", "state": "WA", "meta": "", "link": "http://phish.net/setlists/?d=1998-07-17", "venueid": "248", "showdate": "1998-07-17"}, {"showyear": "1998", "city": "Mountain View", "showid": "1252706478", "relativetime": "15 years ago", "artist": "Phish", "country": "USA", "nicedate": "July 19, 1998", "venue": "Shoreline Amphitheatre", "state": "CA", "meta": "", "link": "http://phish.net/setlists/?d=1998-07-19", "venueid": "247", "showdate": "1998-07-19"}, {"showyear": "1998", "city": "Ventura", "showid": "1252706713", "relativetime": "15 years ago", "artist": "Phish", "country": "USA", "nicedate": "July 20, 1998", "venue": "Ventura County Fairgrounds", "state": "CA", "meta": "", "link": "http://phish.net/setlists/?d=1998-07-20", "venueid": "517", "showdate": "1998-07-20"}, {"showyear": "1998", "city": "Phoenix", "showid": "1252718274", "relativetime": "15 years ago", "artist": "Phish", "country": "USA", "nicedate": "July 21, 1998", "venue": "Desert Sky Pavilion", "state": "AZ", "meta": "", "link": "http://phish.net/setlists/?d=1998-07-21", "venueid": "404", "showdate": "1998-07-21"}, {"showyear": "1998", "city": "The Woodlands", "showid": "1252718417", "relativetime": "15 years ago", "artist": "Phish", "country": "USA", "nicedate": "July 24, 1998", "venue": "Cynthia Woods Mitchell Pavilion", "state": "TX", "meta": "", "link": "http://phish.net/setlists/?d=1998-07-24", "venueid": "416", "showdate": "1998-07-24"}, {"showyear": "1998", "city": "Austin", "showid": "1252718878", "relativetime": "15 years ago", "artist": "Phish", "country": "USA", "nicedate": "July 25, 1998", "venue": "South Park Meadows", "state": "TX", "meta": "", "link": "http://phish.net/setlists/?d=1998-07-25", "venueid": "415", "showdate": "1998-07-25"}, {"showyear": "1998", "city": "Dallas", "showid": "1252719132", "relativetime": "15 years ago", "artist": "Phish", "country": "USA", "nicedate": "July 26, 1998", "venue": "Starplex Amphitheatre", "state": "TX", "meta": "", "link": "http://phish.net/setlists/?d=1998-07-26", "venueid": "516", "showdate": "1998-07-26"}, {"showyear": "1998", "city": "Bonner Springs", "showid": "1252719428", "relativetime": "15 years ago", "artist": "Phish", "country": "USA", "nicedate": "July 28, 1998", "venue": "Sandstone Amphitheatre", "state": "KS", "meta": "", "link": "http://phish.net/setlists/?d=1998-07-28", "venueid": "403", "showdate": "1998-07-28"}, {"showyear": "1998", "city": "Maryland Heights", "showid": "1252719735", "relativetime": "15 years ago", "artist": "Phish", "country": "USA", "nicedate": "July 29, 1998", "venue": "Riverport Amphitheater", "state": "MO", "meta": "", "link": "http://phish.net/setlists/?d=1998-07-29", "venueid": "225", "showdate": "1998-07-29"}, {"showyear": "1998", "city": "Columbus", "showid": "1252719984", "relativetime": "15 years ago", "artist": "Phish", "country": "USA", "nicedate": "July 31, 1998", "venue": "Polaris Amphitheater", "state": "OH", "meta": "", "link": "http://phish.net/setlists/?d=1998-07-31", "venueid": "387", "showdate": "1998-07-31"}, {"showyear": "1998", "city": "East Troy", "showid": "1252720855", "relativetime": "15 years ago", "artist": "Phish", "country": "USA", "nicedate": "August 01, 1998", "venue": "Alpine Valley Music Theatre", "state": "WI", "meta": "", "link": "http://phish.net/setlists/?d=1998-08-01", "venueid": "3", "showdate": "1998-08-01"}, {"showyear": "1998", "city": "Noblesville", "showid": "1252721006", "relativetime": "15 years ago", "artist": "Phish", "country": "USA", "nicedate": "August 02, 1998", "venue": "Deer Creek Music Center", "state": "IN", "meta": "", "link": "http://phish.net/setlists/?d=1998-08-02", "venueid": "401", "showdate": "1998-08-02"}, {"showyear": "1998", "city": "Noblesville", "showid": "1252721303", "relativetime": "15 years ago", "artist": "Phish", "country": "USA", "nicedate": "August 03, 1998", "venue": "Deer Creek Music Center", "state": "IN", "meta": "", "link": "http://phish.net/setlists/?d=1998-08-03", "venueid": "401", "showdate": "1998-08-03"}, {"showyear": "1998", "city": "Atlanta", "showid": "1252721860", "relativetime": "15 years ago", "artist": "Phish", "country": "USA", "nicedate": "August 06, 1998", "venue": "Lakewood Amphitheatre", "state": "GA", "meta": "", "link": "http://phish.net/setlists/?d=1998-08-06", "venueid": "396", "showdate": "1998-08-06"}, {"showyear": "1998", "city": "Raleigh", "showid": "1252722106", "relativetime": "15 years ago", "artist": "Phish", "country": "USA", "nicedate": "August 07, 1998", "venue": "Walnut Creek Amphitheater", "state": "NC", "meta": "", "link": "http://phish.net/setlists/?d=1998-08-07", "venueid": "456", "showdate": "1998-08-07"}, {"showyear": "1998", "city": "Columbia", "showid": "1252722271", "relativetime": "15 years ago", "artist": "Phish", "country": "USA", "nicedate": "August 08, 1998", "venue": "Merriweather Post Pavilion", "state": "MD", "meta": "", "link": "http://phish.net/setlists/?d=1998-08-08", "venueid": "9", "showdate": "1998-08-08"}, {"showyear": "1998", "city": "Virginia Beach", "showid": "1252724010", "relativetime": "15 years ago", "artist": "Phish", "country": "USA", "nicedate": "August 09, 1998", "venue": "Virginia Beach Amphitheater", "state": "VA", "meta": "", "link": "http://phish.net/setlists/?d=1998-08-09", "venueid": "407", "showdate": "1998-08-09"}, {"showyear": "1998", "city": "Burgettstown", "showid": "1252724249", "relativetime": "15 years ago", "artist": "Phish", "country": "USA", "nicedate": "August 11, 1998", "venue": "Star Lake Amphitheatre", "state": "PA", "meta": "", "link": "http://phish.net/setlists/?d=1998-08-11", "venueid": "400", "showdate": "1998-08-11"}, {"showyear": "1998", "city": "Vernon", "showid": "1252724537", "relativetime": "15 years ago", "artist": "Phish", "country": "USA", "nicedate": "August 12, 1998", "venue": "Vernon Downs", "state": "NY", "meta": "", "link": "http://phish.net/setlists/?d=1998-08-12", "venueid": "548", "showdate": "1998-08-12"}, {"showyear": "1998", "city": "Limestone", "showid": "1252731478", "relativetime": "15 years ago", "artist": "Phish", "country": "USA", "nicedate": "August 14, 1998", "venue": "Loring Commerce Center at Loring Air Force Base", "state": "ME", "meta": "", "link": "http://phish.net/setlists/?d=1998-08-14", "venueid": "270", "showdate": "1998-08-14"}, {"showyear": "1998", "city": "Limestone", "showid": "1252731689", "relativetime": "15 years ago", "artist": "Phish", "country": "USA", "nicedate": "August 15, 1998", "venue": "Loring Commerce Center at Loring Air Force Base", "state": "ME", "meta": "", "link": "http://phish.net/setlists/?d=1998-08-15", "venueid": "270", "showdate": "1998-08-15"}, {"showyear": "1998", "city": "Limestone", "showid": "1252732457", "relativetime": "15 years ago", "artist": "Phish", "country": "USA", "nicedate": "August 16, 1998", "venue": "Loring Commerce Center at Loring Air Force Base", "state": "ME", "meta": "", "link": "http://phish.net/setlists/?d=1998-08-16", "venueid": "270", "showdate": "1998-08-16"}, {"showyear": "1998", "city": "Tinley Park", "showid": "1252732922", "relativetime": "15 years ago", "artist": "Phish", "country": "USA", "nicedate": "October 03, 1998", "venue": "New World Music Theatre", "state": "IL", "meta": "", "link": "http://phish.net/setlists/?d=1998-10-03", "venueid": "518", "showdate": "1998-10-03"}, {"showyear": "1998", "city": "San Francisco", "showid": "1252776497", "relativetime": "15 years ago", "artist": "Phish", "country": "USA", "nicedate": "October 15, 1998", "venue": "The Fillmore", "state": "CA", "meta": "", "link": "http://phish.net/setlists/?d=1998-10-15", "venueid": "560", "showdate": "1998-10-15"}, {"showyear": "1998", "city": "Mountain View", "showid": "1252777650", "relativetime": "15 years ago", "artist": "Phish", "country": "USA", "nicedate": "October 17, 1998", "venue": "Shoreline Amphitheatre", "state": "CA", "meta": "", "link": "http://phish.net/setlists/?d=1998-10-17", "venueid": "247", "showdate": "1998-10-17"}, {"showyear": "1998", "city": "Mountain View", "showid": "1252778028", "relativetime": "15 years ago", "artist": "Phish", "country": "USA", "nicedate": "October 18, 1998", "venue": "Shoreline Amphitheatre", "state": "CA", "meta": "", "link": "http://phish.net/setlists/?d=1998-10-18", "venueid": "247", "showdate": "1998-10-18"}, {"showyear": "1998", "city": "New York", "showid": "1252781853", "relativetime": "15 years ago", "artist": "Phish", "country": "USA", "nicedate": "October 20, 1998", "venue": "Sony Music Studios", "state": "NY", "meta": "", "link": "http://phish.net/setlists/?d=1998-10-20", "venueid": "561", "showdate": "1998-10-20"}, {"showyear": "1998", "city": "New York", "showid": "1252781893", "relativetime": "15 years ago", "artist": "Phish", "country": "USA", "nicedate": "October 27, 1998", "venue": "Ed Sullivan Theater", "state": "NY", "meta": "", "link": "http://phish.net/setlists/?d=1998-10-27", "venueid": "228", "showdate": "1998-10-27"}, {"showyear": "1998", "city": "Los Angeles", "showid": "1252782414", "relativetime": "15 years ago", "artist": "Phish", "country": "USA", "nicedate": "October 29, 1998", "venue": "Greek Theatre", "state": "CA", "meta": "", "link": "http://phish.net/setlists/?d=1998-10-29", "venueid": "289", "showdate": "1998-10-29"}, {"showyear": "1998", "city": "Las Vegas", "showid": "1252784901", "relativetime": "15 years ago", "artist": "Phish", "country": "USA", "nicedate": "October 30, 1998", "venue": "Thomas & Mack Center", "state": "NV", "meta": "", "link": "http://phish.net/setlists/?d=1998-10-30", "venueid": "230", "showdate": "1998-10-30"}, {"showyear": "1998", "city": "Las Vegas", "showid": "1252785199", "relativetime": "15 years ago", "artist": "Phish", "country": "USA", "nicedate": "October 31, 1998", "venue": "Thomas & Mack Center", "state": "NV", "meta": "", "link": "http://phish.net/setlists/?d=1998-10-31", "venueid": "230", "showdate": "1998-10-31"}, {"showyear": "1998", "city": "West Valley City", "showid": "1252789376", "relativetime": "15 years ago", "artist": "Phish", "country": "USA", "nicedate": "November 02, 1998", "venue": null, "state": "UT", "meta": "", "link": "http://phish.net/setlists/?d=1998-11-02", "venueid": "520", "showdate": "1998-11-02"}, {"showyear": "1998", "city": "Boulder", "showid": "1252789796", "relativetime": "15 years ago", "artist": "Phish", "country": "USA", "nicedate": "November 03, 1998", "venue": "KBCO Studios", "state": "CO", "meta": "", "link": "http://phish.net/setlists/?d=1998-11-03", "venueid": "570", "showdate": "1998-11-03"}, {"showyear": "1998", "city": "Denver", "showid": "1252789936", "relativetime": "15 years ago", "artist": "Phish", "country": "USA", "nicedate": "November 04, 1998", "venue": "McNichols Arena", "state": "CO", "meta": "", "link": "http://phish.net/setlists/?d=1998-11-04", "venueid": "521", "showdate": "1998-11-04"}, {"showyear": "1998", "city": "Madison", "showid": "1252798611", "relativetime": "15 years ago", "artist": "Phish", "country": "USA", "nicedate": "November 06, 1998", "venue": "Kohl Center", "state": "WI", "meta": "", "link": "http://phish.net/setlists/?d=1998-11-06", "venueid": "572", "showdate": "1998-11-06"}, {"showyear": "1998", "city": "Chicago", "showid": "1252798728", "relativetime": "15 years ago", "artist": "Phish", "country": "USA", "nicedate": "November 07, 1998", "venue": "UIC Pavilion, University of Illinois", "state": "IL", "meta": "", "link": "http://phish.net/setlists/?d=1998-11-07", "venueid": "368", "showdate": "1998-11-07"}, {"showyear": "1998", "city": "Chicago", "showid": "1252801003", "relativetime": "15 years ago", "artist": "Phish", "country": "USA", "nicedate": "November 08, 1998", "venue": "UIC Pavilion, University of Illinois", "state": "IL", "meta": "", "link": "http://phish.net/setlists/?d=1998-11-08", "venueid": "368", "showdate": "1998-11-08"}, {"showyear": "1998", "city": "Chicago", "showid": "1252801188", "relativetime": "15 years ago", "artist": "Phish", "country": "USA", "nicedate": "November 09, 1998", "venue": "UIC Pavilion, University of Illinois", "state": "IL", "meta": "", "link": "http://phish.net/setlists/?d=1998-11-09", "venueid": "368", "showdate": "1998-11-09"}, {"showyear": "1998", "city": "Grand Rapids", "showid": "1252801349", "relativetime": "15 years ago", "artist": "Phish", "country": "USA", "nicedate": "November 11, 1998", "venue": "Van Andel Arena", "state": "MI", "meta": "", "link": "http://phish.net/setlists/?d=1998-11-11", "venueid": "573", "showdate": "1998-11-11"}, {"showyear": "1998", "city": "Cleveland", "showid": "1252801481", "relativetime": "15 years ago", "artist": "Phish", "country": "USA", "nicedate": "November 13, 1998", "venue": "CSU Convocation Center", "state": "OH", "meta": "", "link": "http://phish.net/setlists/?d=1998-11-13", "venueid": "525", "showdate": "1998-11-13"}, {"showyear": "1998", "city": "Cincinnati", "showid": "1252803036", "relativetime": "15 years ago", "artist": "Phish", "country": "USA", "nicedate": "November 14, 1998", "venue": "The Crown", "state": "OH", "meta": "", "link": "http://phish.net/setlists/?d=1998-11-14", "venueid": "574", "showdate": "1998-11-14"}, {"showyear": "1998", "city": "Murfreesboro", "showid": "1252803334", "relativetime": "15 years ago", "artist": "Phish", "country": "USA", "nicedate": "November 15, 1998", "venue": "Murphy Center, Middle Tennessee State University", "state": "TN", "meta": "", "link": "http://phish.net/setlists/?d=1998-11-15", "venueid": "575", "showdate": "1998-11-15"}, {"showyear": "1998", "city": "Greenville", "showid": "1252803554", "relativetime": "15 years ago", "artist": "Phish", "country": "USA", "nicedate": "November 18, 1998", "venue": "BI-LO Center", "state": "SC", "meta": "", "link": "http://phish.net/setlists/?d=1998-11-18", "venueid": "576", "showdate": "1998-11-18"}, {"showyear": "1998", "city": "Winston-Salem", "showid": "1252803721", "relativetime": "15 years ago", "artist": "Phish", "country": "USA", "nicedate": "November 19, 1998", "venue": "Lawrence Joel Veterans Memorial Coliseum", "state": "NC", "meta": "", "link": "http://phish.net/setlists/?d=1998-11-19", "venueid": "38", "showdate": "1998-11-19"}, {"showyear": "1998", "city": "Hampton", "showid": "1252804964", "relativetime": "15 years ago", "artist": "Phish", "country": "USA", "nicedate": "November 20, 1998", "venue": "Hampton Coliseum", "state": "VA", "meta": "", "link": "http://phish.net/setlists/?d=1998-11-20", "venueid": "6", "showdate": "1998-11-20"}, {"showyear": "1998", "city": "Hampton", "showid": "1252805574", "relativetime": "15 years ago", "artist": "Phish", "country": "USA", "nicedate": "November 21, 1998", "venue": "Hampton Coliseum", "state": "VA", "meta": "", "link": "http://phish.net/setlists/?d=1998-11-21", "venueid": "6", "showdate": "1998-11-21"}, {"showyear": "1998", "city": "New Haven", "showid": "1252805758", "relativetime": "15 years ago", "artist": "Phish", "country": "USA", "nicedate": "November 24, 1998", "venue": "New Haven Veterans Memorial Coliseum", "state": "CT", "meta": "", "link": "http://phish.net/setlists/?d=1998-11-24", "venueid": "374", "showdate": "1998-11-24"}, {"showyear": "1998", "city": "Albany", "showid": "1252806518", "relativetime": "15 years ago", "artist": "Phish", "country": "USA", "nicedate": "November 25, 1998", "venue": "Pepsi Arena", "state": "NY", "meta": "", "link": "http://phish.net/setlists/?d=1998-11-25", "venueid": "273", "showdate": "1998-11-25"}, {"showyear": "1998", "city": "Worcester", "showid": "1252806821", "relativetime": "15 years ago", "artist": "Phish", "country": "USA", "nicedate": "November 27, 1998", "venue": "Worcester Centrum Centre", "state": "MA", "meta": "", "link": "http://phish.net/setlists/?d=1998-11-27", "venueid": "241", "showdate": "1998-11-27"}, {"showyear": "1998", "city": "Worcester", "showid": "1252807017", "relativetime": "15 years ago", "artist": "Phish", "country": "USA", "nicedate": "November 28, 1998", "venue": "Worcester Centrum Centre", "state": "MA", "meta": "", "link": "http://phish.net/setlists/?d=1998-11-28", "venueid": "241", "showdate": "1998-11-28"}, {"showyear": "1998", "city": "Worcester", "showid": "1252807243", "relativetime": "15 years ago", "artist": "Phish", "country": "USA", "nicedate": "November 29, 1998", "venue": "Worcester Centrum Centre", "state": "MA", "meta": "", "link": "http://phish.net/setlists/?d=1998-11-29", "venueid": "241", "showdate": "1998-11-29"}, {"showyear": "1998", "city": "New York", "showid": "1252807505", "relativetime": "15 years ago", "artist": "Phish", "country": "USA", "nicedate": "December 28, 1998", "venue": "Madison Square Garden", "state": "NY", "meta": "", "link": "http://phish.net/setlists/?d=1998-12-28", "venueid": "157", "showdate": "1998-12-28"}, {"showyear": "1998", "city": "New York", "showid": "1252807615", "relativetime": "15 years ago", "artist": "Phish", "country": "USA", "nicedate": "December 29, 1998", "venue": "Madison Square Garden", "state": "NY", "meta": "", "link": "http://phish.net/setlists/?d=1998-12-29", "venueid": "157", "showdate": "1998-12-29"}, {"showyear": "1998", "city": "New York", "showid": "1252807808", "relativetime": "15 years ago", "artist": "Phish", "country": "USA", "nicedate": "December 30, 1998", "venue": "Madison Square Garden", "state": "NY", "meta": "", "link": "http://phish.net/setlists/?d=1998-12-30", "venueid": "157", "showdate": "1998-12-30"}, {"showyear": "1998", "city": "New York", "showid": "1252808086", "relativetime": "15 years ago", "artist": "Phish", "country": "USA", "nicedate": "December 31, 1998", "venue": "Madison Square Garden", "state": "NY", "meta": "", "link": "http://phish.net/setlists/?d=1998-12-31", "venueid": "157", "showdate": "1998-12-31"}]